gameworld/envs/__init__.py
gameworld/envs/base/__init__.py
gameworld/envs/base/aviate.py
gameworld/envs/base/base_env.py
gameworld/envs/base/bounce.py
gameworld/envs/base/cross.py
gameworld/envs/base/drive.py
gameworld/envs/base/explode.py
gameworld/envs/base/fruits.py
gameworld/envs/base/gold.py
gameworld/envs/base/hunt.py
gameworld/envs/base/impact.py
gameworld/envs/base/jump.py
gameworld/envs/base/utils.py
gameworld/envs/perturbed/__init__.py
gameworld/envs/perturbed/aviate.py
gameworld/envs/perturbed/bounce.py
gameworld/envs/perturbed/cross.py
gameworld/envs/perturbed/drive.py
gameworld/envs/perturbed/explode.py
gameworld/envs/perturbed/fruits.py
gameworld/envs/perturbed/gold.py
gameworld/envs/perturbed/hunt.py
gameworld/envs/perturbed/impact.py
gameworld/envs/perturbed/jump.py
gameworld-0.1.0.dist-info/licenses/LICENSE
gameworld-0.1.0.dist-info/METADATA
gameworld-0.1.0.dist-info/WHEEL
gameworld-0.1.0.dist-info/top_level.txt
gameworld-0.1.0.dist-info/RECORD
