Metadata-Version: 2.4
Name: gameworld
Version: 0.1.0
Summary: Gameworld: Environments for 2-D Arcade Games in Python
Author-email: VERSES Research <verses.research@verses.ai>
Requires-Python: <3.12,>=3.10
License-File: LICENSE
Requires-Dist: numpy==1.26.4
Requires-Dist: gymnasium==0.29.1
Requires-Dist: imageio==2.36.0
Provides-Extra: test
Requires-Dist: pytest; extra == "test"
Requires-Dist: pytest-cov; extra == "test"
Dynamic: license-file
